{
    "id":"166866264",
    "account_id":"40681",
    "email":null,
    "phone_number":null,
    "title":null,
    "firstname":"Adam",
    "lastname":"Rogas #56445-048",
    "company":"FPC Yankton Federal Prison Camp",
    "job_title":null,
    "address1":"PO BOX 700",
    "address2":"Example street",
    "address3":null,
    "city":"YANKTON",
    "county":"SD",
    "country":"US",
    "postcode":"57078-0700",
    "dps":"00",
    "checksum":"6",
    "ref_id":null,
    "blacklist":"0",
    "paffed_by":"auto"
}
